{
  "schemaVersion": "0.1.0",
  "generatedAt": "2026-04-24T01:30:27.042Z",
  "computedAtSession": "session_088",
  "metrics": {
    "common.L1.cumulativeLearning": {
      "totalDatapoints": 258,
      "nonNullDatapoints": 258,
      "lastComputedSession": "session_088",
      "status": "ok"
    },
    "common.L3.autonomy": {
      "totalDatapoints": 258,
      "nonNullDatapoints": 246,
      "lastComputedSession": "session_088",
      "status": "ok"
    },
    "signature.dev.firstPassRate": {
      "totalDatapoints": 258,
      "nonNullDatapoints": 201,
      "lastComputedSession": "session_088",
      "status": "ok"
    },
    "signature.nova.promotionRate": {
      "totalDatapoints": 246,
      "nonNullDatapoints": 209,
      "lastComputedSession": "session_088",
      "status": "ok"
    }
  }
}
